odoo_domain_converter/__init__.py
odoo_domain_converter/cli.py
odoo_domain_converter/converter.py
odoo_domain_converter/odoo.py
odoo_domain_converter-0.1.0.dist-info/LICENSE
odoo_domain_converter-0.1.0.dist-info/METADATA
odoo_domain_converter-0.1.0.dist-info/WHEEL
odoo_domain_converter-0.1.0.dist-info/entry_points.txt
odoo_domain_converter-0.1.0.dist-info/top_level.txt
odoo_domain_converter-0.1.0.dist-info/RECORD
